regsnp_intron/__init__.py
regsnp_intron/feature_calculator.py
regsnp_intron/conservation/__init__.py
regsnp_intron/conservation/phylop.py
regsnp_intron/junc_score/__init__.py
regsnp_intron/junc_score/junction_strength.py
regsnp_intron/predictor/__init__.py
regsnp_intron/predictor/predictor.py
regsnp_intron/protein_feature/__init__.py
regsnp_intron/protein_feature/fetch_db.py
regsnp_intron/protein_feature/gene_pred_ext.py
regsnp_intron/protein_feature/pfam.py
regsnp_intron/protein_feature/protein_feature.py
regsnp_intron/protein_feature/ptm.py
regsnp_intron/protein_feature/spined.py
regsnp_intron/rbp/__init__.py
regsnp_intron/rbp/rbp.py
regsnp_intron/rbp/rbp_change.py
regsnp_intron/rbp/rbp_score.py
regsnp_intron/settings/settings.json
regsnp_intron/utils/__init__.py
regsnp_intron/utils/annovar.py
regsnp_intron/utils/closest_exon.py
regsnp_intron/utils/seq.py
regsnp_intron/utils/snp.py
regsnp_intron/utils/vcf.py
regsnp_intron-0.1.5.data/scripts/regsnp_intron
regsnp_intron-0.1.5.dist-info/DESCRIPTION.rst
regsnp_intron-0.1.5.dist-info/METADATA
regsnp_intron-0.1.5.dist-info/RECORD
regsnp_intron-0.1.5.dist-info/WHEEL
regsnp_intron-0.1.5.dist-info/metadata.json
regsnp_intron-0.1.5.dist-info/top_level.txt
