Metadata-Version: 2.0
Name: regsnp-intron
Version: 0.1.5
Summary: Predict disease-causing probability of human intronic SNVs.
Home-page: https://github.com/linhai86/regsnp_intron
Author: linhai
Author-email: linhai@iupui.edu
License: MIT
Platform: UNKNOWN
Classifier: Development Status :: 3 - Alpha
Classifier: License :: OSI Approved :: MIT License
Classifier: Programming Language :: Python :: 2.7
Classifier: Topic :: Scientific/Engineering :: Bio-Informatics
Requires-Dist: bx-python
Requires-Dist: numpy
Requires-Dist: pandas
Requires-Dist: pybedtools
Requires-Dist: pysam
Requires-Dist: scipy
Requires-Dist: sklearn
